aioaccount/__init__.py
aioaccount/_const.py
aioaccount/_engines.py
aioaccount/_errors.py
aioaccount/_models.py
aioaccount/_mongo.py
aioaccount/_pass_policy.py
aioaccount/_smtp.py
aioaccount/_sql.py
aioaccount/_user.py
aioaccount/_util.py
aioaccount/tests/__init__.py
aioaccount/tests/args.py
aioaccount/tests/base.py
aioaccount/tests/test_confirm_email.py
aioaccount/tests/test_create_account.py
aioaccount/tests/test_delete_account.py
aioaccount/tests/test_get_user.py
aioaccount/tests/test_login.py
aioaccount/tests/test_password_resets.py
aioaccount/tests/test_to_user.py
aioaccount/tests/test_update_email.py
aioaccount/tests/test_update_password.py
aioaccount/tests/test_users.py
aioaccount-0.0.2.dist-info/LICENSE
aioaccount-0.0.2.dist-info/METADATA
aioaccount-0.0.2.dist-info/WHEEL
aioaccount-0.0.2.dist-info/top_level.txt
aioaccount-0.0.2.dist-info/RECORD
