Metadata-Version: 2.1
Name: aioaccount
Version: 0.0.2
Summary: Utility for user account creation.
Home-page: https://aioaccount.readthedocs.io/en/latest/
Author: WardPearce
Author-email: wardpearce@protonmail.com
License: AGPL-3.0
Platform: UNKNOWN
Requires-Python: >=3.6
License-File: LICENSE
Requires-Dist: bcrypt
Requires-Dist: password-strength
Requires-Dist: databases[postgresql]
Requires-Dist: databases[mysql]
Requires-Dist: databases[sqlite]
Requires-Dist: sqlalchemy (==1.3.20)
Requires-Dist: motor
Requires-Dist: email-validator
Requires-Dist: aiosmtplib
Requires-Dist: async-timeout
Requires-Dist: aiojobs
Requires-Dist: jinja2
Requires-Dist: asynctest
Requires-Dist: cryptography
Requires-Dist: sphinx-material
Requires-Dist: sphinxcontrib-trio
